airrship/__init__.py
airrship/create_repertoire.py
airrship/data/D_3_family_trimming_proportions.csv
airrship/data/D_5_family_trimming_proportions.csv
airrship/data/IGHD_usage.csv
airrship/data/IGHD_usage_gene.csv
airrship/data/IGHJ_usage.csv
airrship/data/IGHJ_usage_gene.csv
airrship/data/IGHV_usage.csv
airrship/data/IGHV_usage_gene.csv
airrship/data/J_family_trimming_proportions.csv
airrship/data/V_family_trimming_proportions.csv
airrship/data/__init__.py
airrship/data/cdr1_kmer_base_usage.csv
airrship/data/cdr2_kmer_base_usage.csv
airrship/data/cdr3_kmer_base_usage.csv
airrship/data/cdr_kmer_base_usage.csv
airrship/data/fwr1_kmer_base_usage.csv
airrship/data/fwr2_kmer_base_usage.csv
airrship/data/fwr3_kmer_base_usage.csv
airrship/data/fwr4_kmer_base_usage.csv
airrship/data/fwr_kmer_base_usage.csv
airrship/data/imgt_human_IGHD.fasta
airrship/data/imgt_human_IGHJ.fasta
airrship/data/imgt_human_IGHV.fasta
airrship/data/mut_freq_per_seq_per_family.csv
airrship/data/np1_first_base_probs.csv
airrship/data/np1_lengths_proportions.csv
airrship/data/np1_transition_probs_per_position_igag.csv
airrship/data/np1_transition_probs_per_position_igdm.csv
airrship/data/np2_first_base_probs.csv
airrship/data/np2_lengths_proportions.csv
airrship/data/np2_transition_probs_per_position_igag.csv
airrship/data/np2_transition_probs_per_position_igdm.csv
airrship-0.1.5.dist-info/LICENSE
airrship-0.1.5.dist-info/METADATA
airrship-0.1.5.dist-info/WHEEL
airrship-0.1.5.dist-info/entry_points.txt
airrship-0.1.5.dist-info/top_level.txt
airrship-0.1.5.dist-info/RECORD
