Metadata-Version: 2.1
Name: airrship
Version: 0.1.5
Summary: Simulation of B cell receptor repertoires
Author-email: Catherine Sutherland <catherine.sutherland@ed.ac.uk>
License: GNU AFFERO GENERAL PUBLIC LICENSE
Keywords: bioinformatics,sequencing,immunology,adaptive immunity,immunoglobulin,adaptive immune receptor repertoires,AIRR-seq,antibody,repertoire sequencing,B cell repertoire
Classifier: Intended Audience :: Science/Research
Classifier: Programming Language :: Python :: 3.7
Classifier: Programming Language :: Python :: 3.8
Classifier: Programming Language :: Python :: 3.9
Classifier: Programming Language :: Python :: 3.10
Classifier: Programming Language :: Python :: 3.11
Requires-Python: >=3.7
License-File: LICENSE
